ppt_style/__init__.py
ppt_style/component.py
ppt_style/master_ppt.py
ppt_style/templates/default.pptx
edge_pptx-1.0.2.dist-info/METADATA
edge_pptx-1.0.2.dist-info/WHEEL
edge_pptx-1.0.2.dist-info/top_level.txt
edge_pptx-1.0.2.dist-info/RECORD
