Metadata-Version: 2.1
Name: edge-pptx
Version: 1.0.2
Summary: 用于生成 PowerPoint 文件的 Python 模块
Home-page: https://github.com/edgeriver/PPTX_edge.git
Author: wangwl
Author-email: 643176574@qq.com
License: MIT
Classifier: Development Status :: 3 - Alpha
Classifier: License :: OSI Approved :: MIT License
Classifier: Programming Language :: Python :: 3
Classifier: Programming Language :: Python :: 3.9
Classifier: Intended Audience :: Developers
Classifier: Topic :: Software Development :: Libraries :: Python Modules
Requires-Python: >=3.6, <=3.12
Requires-Dist: requests (==2.31.0)
Requires-Dist: python-pptx (==0.6.21)
